{
  "updated": "2024-02-08T22:23:36.498Z",
  "archivedVideosCount": "12892",
  "waitingVideosCount": null,
  "stuckVideos": "403",
  "totalRuntime": {
    "hours": "1246.55",
    "days": "51.94"
  },
  "lastArchived": {
    "url": "https://www.youtube.com/watch?v=J_Lwl9XH-jk",
    "lockExpiry": "2024-02-08T15:29:59.041Z"
  },
  "workersHealthCheck": [
    {
      "worker": "kaltrane",
      "last_seen": "2023-02-22T09:42:45.772Z"
    },
    {
      "worker": "kalamar",
      "last_seen": "2024-02-08T22:23:31.282Z"
    },
    {
      "worker": "luther",
      "last_seen": "2022-07-02T15:32:58.699Z"
    }
  ]
}