{
  "updated": "2024-01-29T02:26:25.565Z",
  "archivedVideosCount": "12854",
  "waitingVideosCount": null,
  "stuckVideos": "403",
  "totalRuntime": {
    "hours": "1242.61",
    "days": "51.78"
  },
  "lastArchived": {
    "url": "https://www.youtube.com/watch?v=xufIo90SiQ0",
    "lockExpiry": "2024-01-29T01:33:34.597Z"
  },
  "workersHealthCheck": [
    {
      "worker": "kaltrane",
      "last_seen": "2023-02-22T09:42:45.772Z"
    },
    {
      "worker": "luther",
      "last_seen": "2022-07-02T15:32:58.699Z"
    },
    {
      "worker": "kalamar",
      "last_seen": "2024-01-29T02:26:16.466Z"
    }
  ]
}