{
  "updated": "2024-05-31T14:24:48.425Z",
  "archivedVideosCount": "13318",
  "waitingVideosCount": null,
  "stuckVideos": "372",
  "totalRuntime": {
    "hours": "1274.74",
    "days": "53.11"
  },
  "lastArchived": {
    "url": "https://www.youtube.com/watch?v=7EIjUE_eyRA",
    "lockExpiry": "2024-05-30T21:35:55.655Z"
  },
  "workersHealthCheck": [
    {
      "worker": "kaltrane",
      "last_seen": "2023-02-22T09:42:45.772Z"
    },
    {
      "worker": "luther",
      "last_seen": "2022-07-02T15:32:58.699Z"
    },
    {
      "worker": "kalamar",
      "last_seen": "2024-05-31T14:24:39.279Z"
    }
  ]
}