{
  "updated": "2024-08-22T12:45:24.120Z",
  "archivedVideosCount": "13634",
  "waitingVideosCount": null,
  "stuckVideos": "375",
  "totalRuntime": {
    "hours": "1298.40",
    "days": "54.10"
  },
  "lastArchived": {
    "url": "https://www.youtube.com/watch?v=Nkf6OBpR8ng",
    "lockExpiry": "2024-08-21T18:31:05.131Z"
  },
  "workersHealthCheck": [
    {
      "worker": "kaltrane",
      "last_seen": "2023-02-22T09:42:45.772Z"
    },
    {
      "worker": "kalamar",
      "last_seen": "2024-08-22T12:45:16.789Z"
    },
    {
      "worker": "luther",
      "last_seen": "2022-07-02T15:32:58.699Z"
    }
  ]
}