{
  "updated": "2024-01-30T22:24:15.595Z",
  "archivedVideosCount": "12859",
  "waitingVideosCount": null,
  "stuckVideos": "403",
  "totalRuntime": {
    "hours": "1244.05",
    "days": "51.84"
  },
  "lastArchived": {
    "url": "https://www.youtube.com/watch?v=SeGGrYcsiSc",
    "lockExpiry": "2024-01-30T14:11:12.472Z"
  },
  "workersHealthCheck": [
    {
      "worker": "kaltrane",
      "last_seen": "2023-02-22T09:42:45.772Z"
    },
    {
      "worker": "kalamar",
      "last_seen": "2024-01-30T22:24:08.576Z"
    },
    {
      "worker": "luther",
      "last_seen": "2022-07-02T15:32:58.699Z"
    }
  ]
}